slaccato/__init__.py
slaccato/core.py
slaccato-0.2.1.dist-info/LICENSE
slaccato-0.2.1.dist-info/METADATA
slaccato-0.2.1.dist-info/WHEEL
slaccato-0.2.1.dist-info/top_level.txt
slaccato-0.2.1.dist-info/RECORD
