Metadata-Version: 2.1
Name: slaccato
Version: 0.2.1
Summary: Structured Slack bot framework.
Home-page: https://github.com/peoplefund-tech/slaccato
Author: Dongho Yu
Author-email: n0rr7882@gmail.com
License: MIT
Platform: UNKNOWN
Classifier: Programming Language :: Python :: 3.4
Classifier: Programming Language :: Python :: 3.5
Classifier: Programming Language :: Python :: 3.6
Classifier: Programming Language :: Python :: 3.7
Classifier: Programming Language :: Python :: 3.8
Requires-Python: >=3.4
Requires-Dist: certifi (==2018.8.24)
Requires-Dist: chardet (==3.0.4)
Requires-Dist: idna (==2.7)
Requires-Dist: requests (>=2.19.1)
Requires-Dist: six (==1.11.0)
Requires-Dist: slackclient (==1.3.0)
Requires-Dist: urllib3 (==1.23)
Requires-Dist: websocket-client (==0.53.0)
